hyperglot/__init__.py
hyperglot/checker.py
hyperglot/cli.py
hyperglot/language.py
hyperglot/languages.py
hyperglot/loader.py
hyperglot/orthography.py
hyperglot/parse.py
hyperglot/shaper.py
hyperglot/validate.py
hyperglot/data/aae.yaml
hyperglot/data/aaq.yaml
hyperglot/data/aar.yaml
hyperglot/data/aat.yaml
hyperglot/data/abe.yaml
hyperglot/data/abi.yaml
hyperglot/data/abk.yaml
hyperglot/data/abn.yaml
hyperglot/data/abq.yaml
hyperglot/data/abr.yaml
hyperglot/data/abv.yaml
hyperglot/data/ace.yaml
hyperglot/data/ach.yaml
hyperglot/data/acm.yaml
hyperglot/data/acq.yaml
hyperglot/data/acu.yaml
hyperglot/data/acw.yaml
hyperglot/data/acx.yaml
hyperglot/data/acz.yaml
hyperglot/data/ada.yaml
hyperglot/data/ade.yaml
hyperglot/data/ady.yaml
hyperglot/data/aeb.yaml
hyperglot/data/aec.yaml
hyperglot/data/aer.yaml
hyperglot/data/afb.yaml
hyperglot/data/afr.yaml
hyperglot/data/agq.yaml
hyperglot/data/agr.yaml
hyperglot/data/agx.yaml
hyperglot/data/aha.yaml
hyperglot/data/aht.yaml
hyperglot/data/aii.yaml
hyperglot/data/ain.yaml
hyperglot/data/aiq.yaml
hyperglot/data/ajg.yaml
hyperglot/data/ajp.yaml
hyperglot/data/akk.yaml
hyperglot/data/ale.yaml
hyperglot/data/aln.yaml
hyperglot/data/alq.yaml
hyperglot/data/als.yaml
hyperglot/data/alt.yaml
hyperglot/data/amc.yaml
hyperglot/data/ame.yaml
hyperglot/data/amh.yaml
hyperglot/data/ami.yaml
hyperglot/data/amr.yaml
hyperglot/data/anc.yaml
hyperglot/data/ani.yaml
hyperglot/data/anw.yaml
hyperglot/data/any.yaml
hyperglot/data/aoz.yaml
hyperglot/data/apc.yaml
hyperglot/data/apd.yaml
hyperglot/data/apn.yaml
hyperglot/data/aqc.yaml
hyperglot/data/arb.yaml
hyperglot/data/arg.yaml
hyperglot/data/arl.yaml
hyperglot/data/arn.yaml
hyperglot/data/arq.yaml
hyperglot/data/arr.yaml
hyperglot/data/ars.yaml
hyperglot/data/ary.yaml
hyperglot/data/arz.yaml
hyperglot/data/asa.yaml
hyperglot/data/asm.yaml
hyperglot/data/ast.yaml
hyperglot/data/atv.yaml
hyperglot/data/auc.yaml
hyperglot/data/aud.yaml
hyperglot/data/ava.yaml
hyperglot/data/ave.yaml
hyperglot-0.7.3.dist-info/licenses/LICENSE.txt
hyperglot-0.7.3.dist-info/METADATA
hyperglot-0.7.3.dist-info/WHEEL
hyperglot-0.7.3.dist-info/entry_points.txt
hyperglot-0.7.3.dist-info/top_level.txt
hyperglot-0.7.3.dist-info/RECORD
