Metadata-Version: 2.4
Name: hyperglot
Version: 0.7.3
Summary: Detect language support for font binaries
Home-page: https://github.com/rosettatype/hyperglot
Author: Johannes Neumeier - Rosetta
Author-email: johannes@rosettatype.com
License: GNU GPLv3
Project-URL: Hyperglot web interface, https://hyperglot.rosettatype.com
Classifier: Programming Language :: Python :: 3.8
Classifier: Operating System :: OS Independent
Classifier: License :: OSI Approved :: GNU General Public License v3 (GPLv3)
Classifier: Intended Audience :: End Users/Desktop
Classifier: Intended Audience :: Information Technology
Classifier: Topic :: Text Processing :: Fonts
Classifier: Topic :: Text Processing :: Linguistic
Requires-Python: >3.8.0
License-File: LICENSE.txt
Requires-Dist: click>=7.0
Requires-Dist: fonttools>=4.50.0
Requires-Dist: uharfbuzz>=0.39.0
Requires-Dist: pyyaml>=6.0.0
Requires-Dist: colorlog>=6.4.1
Provides-Extra: dev
Requires-Dist: pytest; extra == "dev"
Requires-Dist: tox; extra == "dev"
Provides-Extra: build
Requires-Dist: build; extra == "build"
Requires-Dist: twine; extra == "build"
Dynamic: author
Dynamic: author-email
Dynamic: classifier
Dynamic: description
Dynamic: description-content-type
Dynamic: home-page
Dynamic: license
Dynamic: license-file
Dynamic: project-url
Dynamic: provides-extra
Dynamic: requires-dist
Dynamic: requires-python
Dynamic: summary
